{
    "studyStart": 1702594331768,
    "PROLIFIC_PID": "613abaa8ef02caba11c47bc3",
    "STUDY_ID": "657b8660a5476e661c4bf8be",
    "SESSION_ID": "657b870d370d7a8d0a8ae264",
    "0f2b8cd7761db9e260835db65a8252.png": {
        "start": 1702594333796,
        "type": "webp",
        "choice": "2"
    },
    "09f2bd0bfad729bcbe1f269639a3b6.png": {
        "start": 1702594355607,
        "type": "webp",
        "choice": "4"
    },
    "31739ddda03c15125868f61ea116c3.png": {
        "start": 1702594365701,
        "type": "webp",
        "choice": "2"
    },
    "e3a1aa9d7cf9d7320742cd0acc6327.jpeg": {
        "start": 1702594380912,
        "type": "webp",
        "choice": "3"
    },
    "a31a989ee473794adf86728c9ea8f8.jpeg": {
        "start": 1702594395037,
        "type": "webp",
        "choice": "4"
    },
    "b4174a3066b9cea27841852d8b4e2a.jpeg": {
        "start": 1702594407021,
        "type": "webp",
        "choice": "3"
    },
    "ef9b11914417dee3325564daf96b73.png": {
        "start": 1702594419298,
        "type": "webp",
        "choice": "2"
    },
    "2471be677868e5c5ecb253ba8307e4.jpeg": {
        "start": 1702594430053,
        "type": "webp",
        "choice": "2"
    },
    "8befd73131ce66b842955a2a379106.jpeg": {
        "start": 1702594439301,
        "type": "webp",
        "choice": "3"
    },
    "feec24c736e25ba805cc53aaccea5a.png": {
        "start": 1702594448714,
        "type": "webp",
        "choice": "4",
        "pageChoice": "good-control"
    }
}