{
    "studyStart": 1702619813451,
    "PROLIFIC_PID": "6539f5f08a354f21c20d7b17",
    "STUDY_ID": "657be948273fde6bc1076be9",
    "SESSION_ID": "657bea0f00255aa9f25223d0",
    "06d0925c8aff85039657342e438c4c.jpeg": {
        "start": 1702619813756,
        "type": "webp",
        "choice": "4"
    },
    "56a8b6d232270e4e66e761930fd1fe.png": {
        "start": 1702619847979,
        "type": "webp",
        "choice": "3"
    },
    "a155191530212a10c3a10ca5b3ccb8.png": {
        "start": 1702619865276,
        "type": "webp",
        "choice": "1"
    },
    "5d8873c49e8dcbb1644c0f95c61c84.png": {
        "start": 1702619899368,
        "type": "webp",
        "choice": "3"
    },
    "465dc551986ef32278221df1aef484.png": {
        "start": 1702619941059,
        "type": "webp",
        "choice": "5"
    },
    "0fcbbb2f405abc15bfa689efaa801d.jpeg": {
        "start": 1702619961289,
        "type": "webp",
        "choice": "2"
    },
    "ec0ae5c068e4298740b76eb638e443.png": {
        "start": 1702619987943,
        "type": "webp",
        "choice": "5"
    },
    "ceb7dccc78819fa88c1937871ae5ce.jpeg": {
        "start": 1702620006120,
        "type": "webp",
        "choice": "4"
    },
    "67fca6b27fcadb817380882d1e221b.jpeg": {
        "start": 1702620021353,
        "type": "webp",
        "choice": "3"
    },
    "b52bcfc13acd89d8681b826d76b908.jpeg": {
        "start": 1702620035297,
        "type": "webp",
        "choice": "1",
        "pageChoice": "good-control"
    }
}