{
    "studyStart": 1702600486753,
    "PROLIFIC_PID": "656ddbef6ee0b1c7b88fd93b",
    "STUDY_ID": "657b9db8f1964d314ca52689",
    "SESSION_ID": "657b9eeaff6a131dd3994e9d",
    "c1baf9115cf031c00512ebda0efb4b.png": {
        "start": 1702600488467,
        "type": "webp",
        "choice": "1"
    },
    "e2b1ef0f63590e82bc5ec130fe4579.png": {
        "start": 1702600543938,
        "type": "webp",
        "choice": "5"
    },
    "88b5d607387ff82c107c4fdac84753.png": {
        "start": 1702600562789,
        "type": "webp",
        "choice": "3"
    },
    "c42317ad177fd966cfce2f735f34c4.png": {
        "start": 1702600585472,
        "type": "webp",
        "choice": "5"
    },
    "ee3334e134d4f728ef7977d8726a6c.png": {
        "start": 1702600601742,
        "type": "webp",
        "choice": "1"
    },
    "922e2d4184cd2fd87667b4ad141325.png": {
        "start": 1702600617994,
        "type": "webp",
        "choice": "5"
    },
    "54e2484701c5f1cb8a137765d550f0.png": {
        "start": 1702600648415,
        "type": "webp",
        "choice": "1"
    },
    "32268feaa59958775d1ed8bc12e44f.png": {
        "start": 1702600661478,
        "type": "webp",
        "choice": "1"
    },
    "e221fa46873999d2bc9363d19df18f.jpeg": {
        "start": 1702600669770,
        "type": "webp",
        "choice": "3"
    },
    "85be38c20bc4705cb66315f0d76375.png": {
        "start": 1702600686039,
        "type": "webp",
        "choice": "5",
        "pageChoice": "good-control"
    }
}