{
    "studyStart": 1702664363164,
    "PROLIFIC_PID": "655230fde7fef552dd82ec2a",
    "STUDY_ID": "657c955fbd1c491e027f5bf6",
    "SESSION_ID": "657c969e2832af573ef2c1bc",
    "0dfa3e2009e52e79f47342bf6847fc.jpeg": {
        "start": 1702664363282,
        "type": "webp",
        "choice": "2"
    },
    "d6e8930d8ea24a893a5916894523cf.jpeg": {
        "start": 1702664375773,
        "type": "webp",
        "choice": "2"
    },
    "4634b12a95df41bacdb25a9c5a8f93.png": {
        "start": 1702664409539,
        "type": "webp",
        "choice": "3"
    },
    "4ea2828e6e84e47408bbeacd61aa7b.png": {
        "start": 1702664441642,
        "type": "webp",
        "choice": "2"
    },
    "5bd6731417ce4f1242a767d3c612c9.jpeg": {
        "start": 1702664464872,
        "type": "webp",
        "choice": "1"
    },
    "854541120fa24c03a541466ee02ae5.jpeg": {
        "start": 1702664493778,
        "type": "webp",
        "choice": "4"
    },
    "184def23cef05f1decf67918433d20.png": {
        "start": 1702664523111,
        "type": "webp",
        "choice": "1"
    },
    "3c75ed77b1bfe3d434c07d81f23893.jpeg": {
        "start": 1702664539617,
        "type": "webp",
        "choice": "2"
    },
    "707572328f82f46068be691608c3ef.png": {
        "start": 1702664562299,
        "type": "webp",
        "choice": "3"
    },
    "0ce6a324827a9a58ba1490a5f5cb8e.jpeg": {
        "start": 1702664591486,
        "type": "webp",
        "choice": "4",
        "pageChoice": "good-control"
    }
}