{
    "studyStart": 1702683537933,
    "PROLIFIC_PID": "607a3daa5e5eefa6a427b054",
    "STUDY_ID": "657ce24e82cc8185e4ede7d2",
    "SESSION_ID": "657ce2e1f2a25d93bc1afa39",
    "ccf1a2773cb5a70a4094a3ee80531d.jpeg": {
        "start": 1702683538637,
        "type": "webp",
        "choice": "2"
    },
    "ed65a4cc97a54e15709c4b34faa150.png": {
        "start": 1702683563382,
        "type": "webp",
        "choice": "1"
    },
    "0f55dc2eba0c085a1d2c1de315d62c.jpeg": {
        "start": 1702683592834,
        "type": "webp",
        "choice": "3"
    },
    "8b75ed5fbdeb66f1f951da4e064ea7.png": {
        "start": 1702683608725,
        "type": "webp",
        "choice": "2"
    },
    "5edf1da45f529809e20acdc3933b09.jpeg": {
        "start": 1702683634508,
        "type": "webp",
        "choice": "3"
    },
    "549094a995e551eb7ea19dbf86fc10.jpeg": {
        "start": 1702683651104,
        "type": "webp",
        "choice": "4"
    },
    "8185ba36ea6a9a7e3bc87f74c86600.jpeg": {
        "start": 1702683670264,
        "type": "webp",
        "choice": "3"
    },
    "19527595e6e3d169d4966e646cd9b5.png": {
        "start": 1702683680897,
        "type": "webp",
        "choice": "4"
    },
    "e75cb9bb472d7799112109aed3141f.png": {
        "start": 1702683697046,
        "type": "webp",
        "choice": "4"
    },
    "cefced77130737df5abee418651ddf.png": {
        "start": 1702683714289,
        "type": "webp",
        "choice": "2",
        "pageChoice": "good-control"
    }
}