{
    "studyStart": 1702515817442,
    "PROLIFIC_PID": "5ead7d6e96a62440b21c25f8",
    "STUDY_ID": "657a5210b6f42886bef0f5b8",
    "SESSION_ID": "657a541b89695ed70e5ed6e1",
    "12e6faa0aa2170410054b252a958d5.jpeg": {
        "start": 1702515817944,
        "type": "avif",
        "choice": "1"
    },
    "f625bd18b90883828f9fe3ded516a4.png": {
        "start": 1702515843770,
        "type": "avif",
        "choice": "1"
    },
    "09940e9620a6389d22c7fcf2a2a21b.png": {
        "start": 1702515860598,
        "type": "avif",
        "choice": "3"
    },
    "e949a1709fb1ac617d6a00f6ea6d38.jpeg": {
        "start": 1702515869684,
        "type": "avif",
        "choice": "1"
    },
    "a1ce06b018a81f99060f28227b1396.jpeg": {
        "start": 1702515879224,
        "type": "avif",
        "choice": "3"
    },
    "ae9681b63d529c1d188a36391bbb70.jpeg": {
        "start": 1702515888768,
        "type": "avif",
        "choice": "3"
    },
    "c062acb5030b5ff2d2ea74d80d8be9.jpeg": {
        "start": 1702515896406,
        "type": "avif",
        "choice": "3"
    },
    "67212ed0d1c992834d2743a3ea494c.jpeg": {
        "start": 1702515905422,
        "type": "avif",
        "choice": "2"
    },
    "15ae1a42098de30e433e03b32776a5.jpeg": {
        "start": 1702515916527,
        "type": "avif",
        "choice": "3"
    },
    "5b84471dbebfd8485d185e23b10bc8.png": {
        "start": 1702515923185,
        "type": "avif",
        "choice": "3",
        "pageChoice": "good-control"
    }
}