{
    "studyStart": 1702564123357,
    "PROLIFIC_PID": "655e7a52868948670d16b02a",
    "STUDY_ID": "657b0ee23b72c798369e26cd",
    "SESSION_ID": "657b10dcc39ba33b6280f877",
    "5c6cd8437b9b4d161c994e4685123e.jpeg": {
        "start": 1702564123585,
        "type": "avif",
        "choice": "5"
    },
    "7ff10cccbe980b232ac54cc9e3723d.jpeg": {
        "start": 1702564183658,
        "type": "avif",
        "choice": "1"
    },
    "3edd6622be84ec7ea0bdae2049fa9c.png": {
        "start": 1702564204330,
        "type": "avif",
        "choice": "1"
    },
    "753627cabb7faa3bed8571826089e9.png": {
        "start": 1702564219871,
        "type": "avif",
        "choice": "5"
    },
    "8e4053084483a9ef7de99b367a3b22.jpeg": {
        "start": 1702564236535,
        "type": "avif",
        "choice": "1"
    },
    "303d0891ef4825b12af2eddca3206b.jpeg": {
        "start": 1702564295325,
        "type": "avif",
        "choice": "4"
    },
    "382638e455ef54206a3b6d0a75fbf5.jpeg": {
        "start": 1702564310266,
        "type": "avif",
        "choice": "5"
    },
    "b2c1186fe09777cec249bd2c8b6191.png": {
        "start": 1702564325563,
        "type": "avif",
        "choice": "1"
    },
    "adf6439166a4af6faac99c372c4b30.png": {
        "start": 1702564338847,
        "type": "avif",
        "choice": "1"
    },
    "e63bd738cc62628a05f1e7d632b545.png": {
        "start": 1702564350179,
        "type": "avif",
        "choice": "5",
        "pageChoice": "good-control"
    }
}