{
    "studyStart": 1702494511385,
    "PROLIFIC_PID": "5e5d66f2101bf703d65326bc",
    "STUDY_ID": "657a0022f29f614f24f10088",
    "SESSION_ID": "657a0082d24232e14b1ffcd7",
    "c8edc12671ff971883ed46e4fe9f3b.png": {
        "start": 1702494512030,
        "type": "avif",
        "choice": "3"
    },
    "0b0a38cb3414ba406c74e4d7910c82.jpeg": {
        "start": 1702494542462,
        "type": "avif",
        "choice": "3"
    },
    "42f637ecf9d1133b586b3329d8b4ed.png": {
        "start": 1702494556556,
        "type": "avif",
        "choice": "2"
    },
    "ec80198dceb837d164ab15591cfaba.jpeg": {
        "start": 1702494572227,
        "type": "avif",
        "choice": "3"
    },
    "2ba95e8d82492afe9ceb6931e124af.jpeg": {
        "start": 1702494586293,
        "type": "avif",
        "choice": "2"
    },
    "64a14b6bc07f4accc5b4169c86ed00.png": {
        "start": 1702494598040,
        "type": "avif",
        "choice": "2"
    },
    "3dcdca384c5a9cdc09528c60b0dc54.png": {
        "start": 1702494612965,
        "type": "avif",
        "choice": "3"
    },
    "a18d19399c9ae663cc1b0db8fce0a8.jpeg": {
        "start": 1702494638822,
        "type": "avif",
        "choice": "4"
    },
    "6930498b21c84ea23436c5e53f2010.jpeg": {
        "start": 1702494662566,
        "type": "avif",
        "choice": "3"
    },
    "7364f8f704252093793d20bd68286d.jpeg": {
        "start": 1702494679394,
        "type": "avif",
        "choice": "3",
        "pageChoice": "good-control"
    }
}